sortedm2m/__init__.py
sortedm2m/compat.py
sortedm2m/fields.py
sortedm2m/forms.py
sortedm2m/models.py
sortedm2m/operations.py
sortedm2m/locale/cs/LC_MESSAGES/django.mo
sortedm2m/locale/cs/LC_MESSAGES/django.po
sortedm2m/locale/de/LC_MESSAGES/django.mo
sortedm2m/locale/de/LC_MESSAGES/django.po
sortedm2m/locale/es/.DS_Store
sortedm2m/locale/es/LC_MESSAGES/django.mo
sortedm2m/locale/es/LC_MESSAGES/django.po
sortedm2m/locale/fr/LC_MESSAGES/django.mo
sortedm2m/locale/fr/LC_MESSAGES/django.po
sortedm2m/static/sortedm2m/jquery-ui.js
sortedm2m/static/sortedm2m/selector-search.gif
sortedm2m/static/sortedm2m/widget.css
sortedm2m/static/sortedm2m/widget.js
sortedm2m/templates/sortedm2m/sorted_checkbox_select_multiple_widget.html
django_sortedm2m-3.0.1.dist-info/AUTHORS.rst
django_sortedm2m-3.0.1.dist-info/LICENSE.txt
django_sortedm2m-3.0.1.dist-info/METADATA
django_sortedm2m-3.0.1.dist-info/WHEEL
django_sortedm2m-3.0.1.dist-info/top_level.txt
django_sortedm2m-3.0.1.dist-info/RECORD
